Shodan/__init__.py
Shodan/cli_jib.py
Shodan/shodan_temp.py
Shodan/IPResult/__init__.py
Shodan/IPResult/general_information.py
Shodan/IPResult/ip_result.py
Shodan/IPResult/open_ports.py
Shodan/IPResult/vulnerabilities.py
Shodan/IPResult/web_technologies.py
Shodan/URLResult/__init__.py
shox-0.1.5.dist-info/METADATA
shox-0.1.5.dist-info/WHEEL
shox-0.1.5.dist-info/entry_points.txt
shox-0.1.5.dist-info/top_level.txt
shox-0.1.5.dist-info/RECORD
