Metadata-Version: 2.1
Name: shox
Version: 0.1.5
Summary: A powerful tool that combines the port-scanning and OSINT-gathering capabilities of shodan.io with the onhand downloadable exploits of ExploitDB.
Home-page: https://gitlab.com/JIbald/shox
Author: Vadin02
Classifier: Development Status :: 3 - Alpha
Classifier: Intended Audience :: Developers
Classifier: License :: OSI Approved :: MIT License
Classifier: Programming Language :: Python :: 3
Classifier: Programming Language :: Python :: 3.6
Classifier: Programming Language :: Python :: 3.7
Classifier: Programming Language :: Python :: 3.8
Classifier: Programming Language :: Python :: 3.9
Requires-Dist: flask
Requires-Dist: flasgger
Requires-Dist: click
Requires-Dist: requests
Requires-Dist: beautifulsoup4
Requires-Dist: selenium
